[
  {
    "movie": "The Raja Saab [2D | Telugu]",
    "venue": "Miraj Cinemas: MDR Mall, Chandrapur",
    "address": "MDR Mall and Multiplex, Survey No.-59, Wadgaon Bapat Nagar, Chandrapur, Maharashtra 442401, India",
    "chain": "Miraj Cinemas",
    "time": "08:00 AM",
    "audi": "",
    "session_id": "33255",
    "totalSeats": 228,
    "available": 202,
    "sold": 26,
    "gross": 6120.0,
    "minsLeft": 188.8,
    "city": "Chandrapur",
    "state": "Maharashtra",
    "source": "BMS",
    "date": "20260110"
  },
  {
    "movie": "The Raja Saab [2D | Telugu]",
    "venue": "MOVIE TIME: Crystal Mall",
    "address": "2nd Floor, Crystal Mall, Kalawad Road, Rajkot, Gujarat 360005, India",
    "chain": "MOVIETIME",
    "time": "08:00 AM",
    "audi": "",
    "session_id": "18383",
    "totalSeats": 278,
    "available": 250,
    "sold": 28,
    "gross": 7200.0,
    "minsLeft": 188.7,
    "city": "Rajkot",
    "state": "Gujarat",
    "source": "BMS",
    "date": "20260110"
  },
  {
    "movie": "The Raja Saab [2D | Telugu]",
    "venue": "INOX: Rajkot R World",
    "address": "Old Dharam Cinema Building, Kasturba Road, Naval Nagar, Near Saurashtra Cricket Association, Rajkot, Gujarat 360001, India",
    "chain": "INOX",
    "time": "08:00 AM",
    "audi": "",
    "session_id": "56624",
    "totalSeats": 182,
    "available": 170,
    "sold": 12,
    "gross": 2040.0,
    "minsLeft": 188.6,
    "city": "Rajkot",
    "state": "Gujarat",
    "source": "BMS",
    "date": "20260110"
  },
  {
    "movie": "The Raja Saab [2D | Telugu]",
    "venue": "Sri Melody HDR Dolby Atmos: Vizag",
    "address": "Suryabagh, Jagadamba Junction, V Max Theatre, Vizag, Andhra Pradesh 530020, India",
    "chain": "Melody Theatre: Vizag",
    "time": "06:30 AM",
    "audi": "",
    "session_id": "11653",
    "totalSeats": 774,
    "available": 179,
    "sold": 595,
    "gross": 163175.0,
    "minsLeft": 97.1,
    "city": "Vizag",
    "state": "Andhra Pradesh",
    "source": "BMS",
    "date": "20260110"
  },
  {
    "movie": "The Raja Saab [2D | Telugu]",
    "venue": "INOX: CMR Central, Gajuwaka",
    "address": "INOX Leisure Limited, 3rd Floor, CMR Central, Chaitanya Nagar, NH 5, Gajuwaka, Vizag (Visakhapatnam), Andhra Pradesh 530026, India",
    "chain": "INOX",
    "time": "08:00 AM",
    "audi": "",
    "session_id": "17580",
    "totalSeats": 220,
    "available": 190,
    "sold": 30,
    "gross": 11310.0,
    "minsLeft": 187.1,
    "city": "Vizag (Visakhapatnam)",
    "state": "Andhra Pradesh",
    "source": "BMS",
    "date": "20260110"
  },
  {
    "movie": "The Raja Saab [2D | Telugu]",
    "venue": "Cinepolis: Sreekanya Cineglitz, Madhurawada",
    "address": "100 Feet Road, Madhurawada, Vizag (Visakhapatnam), Andhra Pradesh 530048, India",
    "chain": "Cinepolis",
    "time": "08:00 AM",
    "audi": "",
    "session_id": "41713",
    "totalSeats": 225,
    "available": 204,
    "sold": 21,
    "gross": 7917.0,
    "minsLeft": 187.1,
    "city": "Vizag (Visakhapatnam)",
    "state": "Andhra Pradesh",
    "source": "BMS",
    "date": "20260110"
  },
  {
    "movie": "The Raja Saab [2D | Telugu]",
    "venue": "Jagadamba Complex A/C 4K Dolby Atmos : Vizag",
    "address": "Chitralaya Road, Jagadamba Junction, Near South Indian Bank ATM, Vizag, Andhra Pradesh 530020, India",
    "chain": "Jagadamba Cinemas: Vizag",
    "time": "07:00 AM",
    "audi": "JAGADAMBA",
    "session_id": "36454",
    "totalSeats": 886,
    "available": 367,
    "sold": 519,
    "gross": 141040.0,
    "minsLeft": 127.0,
    "city": "Vizag",
    "state": "Andhra Pradesh",
    "source": "BMS",
    "date": "20260110"
  },
  {
    "movie": "The Raja Saab [2D | Telugu]",
    "venue": "Krishna Miniplex 2K Dolby, IT Sez: Madhurawada",
    "address": "Infosys lane, Beside Area 51 Coffee Shop, Rushikonda, Near IT Sez, Hill no. 2, Vizag (Visakhapatnam), Andhra Pradesh 530045, India",
    "chain": "Krishna Miniplex: Vizag",
    "time": "07:00 AM",
    "audi": "",
    "session_id": "13467",
    "totalSeats": 91,
    "available": 87,
    "sold": 4,
    "gross": 1600.0,
    "minsLeft": 126.9,
    "city": "Vizag (Visakhapatnam)",
    "state": "Andhra Pradesh",
    "source": "BMS",
    "date": "20260110"
  }
]