[
  {
    "movie": "Akhanda 2: Thaandavam [2D | Telugu]",
    "city": "Nellimarla",
    "state": "Andhra Pradesh",
    "venue": "SVC S3 Cinema 70MM AC Dolby 7.1, Nellimarla",
    "address": "5C9X+GPR, Nellimarla, Andhra Pradesh 535217, India",
    "time": "06:15 PM",
    "audi": "SVC S3 CINEMAS SRI SATYA 70MM AC Dolby 7.1",
    "session_id": "",
    "totalSeats": 305,
    "available": 225,
    "sold": 80,
    "gross": 8000,
    "occupancy": "26.23%",
    "source": "District",
    "date": "20260109",
    "chain": "Svc Sangeetha"
  },
  {
    "movie": "Akhanda 2: Thaandavam [2D | Telugu]",
    "city": "Nellimarla",
    "state": "Andhra Pradesh",
    "venue": "SVC S3 Cinema 70MM AC Dolby 7.1, Nellimarla",
    "address": "5C9X+GPR, Nellimarla, Andhra Pradesh 535217, India",
    "time": "09:30 PM",
    "audi": "SVC S3 CINEMAS SRI SATYA 70MM AC Dolby 7.1",
    "session_id": "",
    "totalSeats": 305,
    "available": 225,
    "sold": 80,
    "gross": 8000,
    "occupancy": "26.23%",
    "source": "District",
    "date": "20260109",
    "chain": "Svc Sangeetha"
  },
  {
    "movie": "Akhanda 2: Thaandavam [2D | Telugu]",
    "city": "Nellimarla",
    "state": "Andhra Pradesh",
    "venue": "SVC S3 Cinema 70MM AC Dolby 7.1, Nellimarla",
    "address": "5C9X+GPR, Nellimarla, Andhra Pradesh 535217, India",
    "time": "02:30 PM",
    "audi": "SVC S3 CINEMAS SRI SATYA 70MM AC Dolby 7.1",
    "session_id": "",
    "totalSeats": 305,
    "available": 225,
    "sold": 80,
    "gross": 8000,
    "occupancy": "26.23%",
    "source": "District",
    "date": "20260109",
    "chain": "Svc Sangeetha"
  },
  {
    "movie": "Akhanda 2: Thaandavam [2D | Telugu]",
    "city": "Nellimarla",
    "state": "Andhra Pradesh",
    "venue": "SVC S3 Cinema 70MM AC Dolby 7.1, Nellimarla",
    "address": "5C9X+GPR, Nellimarla, Andhra Pradesh 535217, India",
    "time": "11:00 AM",
    "audi": "SVC S3 CINEMAS SRI SATYA 70MM AC Dolby 7.1",
    "session_id": "",
    "totalSeats": 305,
    "available": 225,
    "sold": 80,
    "gross": 8000,
    "occupancy": "26.23%",
    "source": "District",
    "date": "20260109",
    "chain": "Svc Sangeetha"
  },
  {
    "movie": "Missterious [2D | Telugu]",
    "city": "Amangal",
    "state": "Telangana",
    "venue": "Sri Venkateswara Theatre, Ranga Reddy, Amangal",
    "address": "RGWH VVW, Amangal Ranga Reddy District, Amangal, Telangana 509321, India",
    "time": "02:00 PM",
    "audi": "SCREEN-2",
    "session_id": "",
    "totalSeats": 141,
    "available": 111,
    "sold": 30,
    "gross": 850,
    "occupancy": "21.28%",
    "source": "District",
    "date": "20260109",
    "chain": "Ticketnew"
  },
  {
    "movie": "Missterious [2D | Telugu]",
    "city": "Amangal",
    "state": "Telangana",
    "venue": "Sri Venkateswara Theatre, Ranga Reddy, Amangal",
    "address": "RGWH VVW, Amangal Ranga Reddy District, Amangal, Telangana 509321, India",
    "time": "06:00 PM",
    "audi": "SCREEN-2",
    "session_id": "",
    "totalSeats": 141,
    "available": 111,
    "sold": 30,
    "gross": 850,
    "occupancy": "21.28%",
    "source": "District",
    "date": "20260109",
    "chain": "Ticketnew"
  },
  {
    "movie": "Missterious [2D | Telugu]",
    "city": "Amangal",
    "state": "Telangana",
    "venue": "Sri Venkateswara Theatre, Ranga Reddy, Amangal",
    "address": "RGWH VVW, Amangal Ranga Reddy District, Amangal, Telangana 509321, India",
    "time": "11:00 AM",
    "audi": "SCREEN-2",
    "session_id": "",
    "totalSeats": 141,
    "available": 111,
    "sold": 30,
    "gross": 850,
    "occupancy": "21.28%",
    "source": "District",
    "date": "20260109",
    "chain": "Ticketnew"
  },
  {
    "movie": "Missterious [2D | Telugu]",
    "city": "Amangal",
    "state": "Telangana",
    "venue": "Sri Venkateswara Theatre, Ranga Reddy, Amangal",
    "address": "RGWH VVW, Amangal Ranga Reddy District, Amangal, Telangana 509321, India",
    "time": "09:00 PM",
    "audi": "SCREEN-2",
    "session_id": "",
    "totalSeats": 141,
    "available": 111,
    "sold": 30,
    "gross": 850,
    "occupancy": "21.28%",
    "source": "District",
    "date": "20260109",
    "chain": "Ticketnew"
  },
  {
    "movie": "Jana Nayagan [2D | Tamil]",
    "city": "Anaikatti",
    "state": "Kerala",
    "venue": "City Cinema 2K A/C, Anaikatti",
    "address": "Anaikatti, Anaikatti, Kerala 678581, India",
    "time": "06:30 PM",
    "audi": "SCREEN 1",
    "session_id": "",
    "totalSeats": 236,
    "available": 143,
    "sold": 93,
    "gross": 9300,
    "occupancy": "39.41%",
    "source": "District",
    "date": "20260109",
    "chain": "Ticketnew"
  },
  {
    "movie": "Jana Nayagan [2D | Tamil]",
    "city": "Anaikatti",
    "state": "Kerala",
    "venue": "City Cinema 2K A/C, Anaikatti",
    "address": "Anaikatti, Anaikatti, Kerala 678581, India",
    "time": "10:00 PM",
    "audi": "SCREEN 1",
    "session_id": "",
    "totalSeats": 236,
    "available": 147,
    "sold": 89,
    "gross": 8900,
    "occupancy": "37.71%",
    "source": "District",
    "date": "20260109",
    "chain": "Ticketnew"
  },
  {
    "movie": "Jana Nayagan [2D | Tamil]",
    "city": "Anaikatti",
    "state": "Kerala",
    "venue": "City Cinema 2K A/C, Anaikatti",
    "address": "Anaikatti, Anaikatti, Kerala 678581, India",
    "time": "03:15 PM",
    "audi": "SCREEN 1",
    "session_id": "",
    "totalSeats": 236,
    "available": 146,
    "sold": 90,
    "gross": 9000,
    "occupancy": "38.14%",
    "source": "District",
    "date": "20260109",
    "chain": "Ticketnew"
  },
  {
    "movie": "Jana Nayagan [2D | Tamil]",
    "city": "Anaikatti",
    "state": "Kerala",
    "venue": "City Cinema 2K A/C, Anaikatti",
    "address": "Anaikatti, Anaikatti, Kerala 678581, India",
    "time": "12:15 PM",
    "audi": "SCREEN 1",
    "session_id": "",
    "totalSeats": 236,
    "available": 79,
    "sold": 157,
    "gross": 15700,
    "occupancy": "66.53%",
    "source": "District",
    "date": "20260109",
    "chain": "Ticketnew"
  },
  {
    "movie": "Jana Nayagan [2D | Tamil]",
    "city": "Bengaluru",
    "state": "Karnataka",
    "venue": "Innovative Multiplex Marathahalli, Near Marathalli Junction, Bengaluru",
    "address": "No.135, Outer Ring Road Varthur Hobli Marathahalli, Near Marathalli Junction, Bengaluru, Karnataka 560037, India",
    "time": "06:25 AM",
    "audi": "Screen3",
    "session_id": "",
    "totalSeats": 352,
    "available": 5,
    "sold": 347,
    "gross": 323400,
    "occupancy": "98.58%",
    "source": "District",
    "date": "20260109",
    "chain": "Suresh Production"
  },
  {
    "movie": "Jana Nayagan [2D | Tamil]",
    "city": "Bengaluru",
    "state": "Karnataka",
    "venue": "Innovative Multiplex Marathahalli, Near Marathalli Junction, Bengaluru",
    "address": "No.135, Outer Ring Road Varthur Hobli Marathahalli, Near Marathalli Junction, Bengaluru, Karnataka 560037, India",
    "time": "06:35 AM",
    "audi": "Screen1",
    "session_id": "",
    "totalSeats": 350,
    "available": 6,
    "sold": 344,
    "gross": 320600,
    "occupancy": "98.29%",
    "source": "District",
    "date": "20260109",
    "chain": "Suresh Production"
  },
  {
    "movie": "Jana Nayagan [2D | Tamil]",
    "city": "Bengaluru",
    "state": "Karnataka",
    "venue": "Innovative Multiplex Marathahalli, Near Marathalli Junction, Bengaluru",
    "address": "No.135, Outer Ring Road Varthur Hobli Marathahalli, Near Marathalli Junction, Bengaluru, Karnataka 560037, India",
    "time": "06:55 AM",
    "audi": "Screen5",
    "session_id": "",
    "totalSeats": 89,
    "available": 24,
    "sold": 65,
    "gross": 58500,
    "occupancy": "73.03%",
    "source": "District",
    "date": "20260109",
    "chain": "Suresh Production"
  },
  {
    "movie": "Jana Nayagan [2D | Tamil]",
    "city": "Bengaluru",
    "state": "Karnataka",
    "venue": "Innovative Multiplex Marathahalli, Near Marathalli Junction, Bengaluru",
    "address": "No.135, Outer Ring Road Varthur Hobli Marathahalli, Near Marathalli Junction, Bengaluru, Karnataka 560037, India",
    "time": "06:15 AM",
    "audi": "Screen2",
    "session_id": "",
    "totalSeats": 352,
    "available": 0,
    "sold": 352,
    "gross": 328000,
    "occupancy": "100.0%",
    "source": "District",
    "date": "20260109",
    "chain": "Suresh Production"
  },
  {
    "movie": "Jana Nayagan [2D | Tamil]",
    "city": "Bengaluru",
    "state": "Karnataka",
    "venue": "Innovative Multiplex Marathahalli, Near Marathalli Junction, Bengaluru",
    "address": "No.135, Outer Ring Road Varthur Hobli Marathahalli, Near Marathalli Junction, Bengaluru, Karnataka 560037, India",
    "time": "07:05 AM",
    "audi": "Screen6",
    "session_id": "",
    "totalSeats": 89,
    "available": 33,
    "sold": 56,
    "gross": 50400,
    "occupancy": "62.92%",
    "source": "District",
    "date": "20260109",
    "chain": "Suresh Production"
  },
  {
    "movie": "Jana Nayagan [2D | Tamil]",
    "city": "Bengaluru",
    "state": "Karnataka",
    "venue": "Balaji 4K Atmos 3D Cinema, Chikkalasandra Uttarahalli Main Road, Bengaluru",
    "address": "Balaji Cinemas, 64/1, Krishna Towers, Uttarahalli Main Road, Chikkalsandra, Bengaluru, Karnataka 560061, India",
    "time": "12:50 PM",
    "audi": "Screen 2",
    "session_id": "",
    "totalSeats": 290,
    "available": 249,
    "sold": 41,
    "gross": 14350,
    "occupancy": "14.14%",
    "source": "District",
    "date": "20260109",
    "chain": "Balaji 4k Atmos Cinemas"
  },
  {
    "movie": "Jana Nayagan [2D | Tamil]",
    "city": "Bengaluru",
    "state": "Karnataka",
    "venue": "Balaji 4K Atmos 3D Cinema, Chikkalasandra Uttarahalli Main Road, Bengaluru",
    "address": "Balaji Cinemas, 64/1, Krishna Towers, Uttarahalli Main Road, Chikkalsandra, Bengaluru, Karnataka 560061, India",
    "time": "09:30 AM",
    "audi": "Screen 1",
    "session_id": "",
    "totalSeats": 329,
    "available": 250,
    "sold": 79,
    "gross": 27650,
    "occupancy": "24.01%",
    "source": "District",
    "date": "20260109",
    "chain": "Balaji 4k Atmos Cinemas"
  },
  {
    "movie": "Jana Nayagan [2D | Tamil]",
    "city": "Bengaluru",
    "state": "Karnataka",
    "venue": "Balaji 4K Atmos 3D Cinema, Chikkalasandra Uttarahalli Main Road, Bengaluru",
    "address": "Balaji Cinemas, 64/1, Krishna Towers, Uttarahalli Main Road, Chikkalsandra, Bengaluru, Karnataka 560061, India",
    "time": "04:10 PM",
    "audi": "Screen 1",
    "session_id": "",
    "totalSeats": 329,
    "available": 304,
    "sold": 25,
    "gross": 8750,
    "occupancy": "7.6%",
    "source": "District",
    "date": "20260109",
    "chain": "Balaji 4k Atmos Cinemas"
  },
  {
    "movie": "Jana Nayagan [2D | Tamil]",
    "city": "Bengaluru",
    "state": "Karnataka",
    "venue": "Balaji 4K Atmos 3D Cinema, Chikkalasandra Uttarahalli Main Road, Bengaluru",
    "address": "Balaji Cinemas, 64/1, Krishna Towers, Uttarahalli Main Road, Chikkalsandra, Bengaluru, Karnataka 560061, India",
    "time": "10:45 PM",
    "audi": "Screen 1",
    "session_id": "",
    "totalSeats": 329,
    "available": 286,
    "sold": 43,
    "gross": 15050,
    "occupancy": "13.07%",
    "source": "District",
    "date": "20260109",
    "chain": "Balaji 4k Atmos Cinemas"
  },
  {
    "movie": "Jana Nayagan [2D | Tamil]",
    "city": "Bengaluru",
    "state": "Karnataka",
    "venue": "Balaji 4K Atmos 3D Cinema, Chikkalasandra Uttarahalli Main Road, Bengaluru",
    "address": "Balaji Cinemas, 64/1, Krishna Towers, Uttarahalli Main Road, Chikkalsandra, Bengaluru, Karnataka 560061, India",
    "time": "07:30 PM",
    "audi": "Screen 2",
    "session_id": "",
    "totalSeats": 290,
    "available": 219,
    "sold": 71,
    "gross": 24850,
    "occupancy": "24.48%",
    "source": "District",
    "date": "20260109",
    "chain": "Balaji 4k Atmos Cinemas"
  },
  {
    "movie": "Jana Nayagan [2D | Tamil]",
    "city": "Bengaluru",
    "state": "Karnataka",
    "venue": "Balaji 4K Atmos 3D Cinema, Chikkalasandra Uttarahalli Main Road, Bengaluru",
    "address": "Balaji Cinemas, 64/1, Krishna Towers, Uttarahalli Main Road, Chikkalsandra, Bengaluru, Karnataka 560061, India",
    "time": "06:15 AM",
    "audi": "Screen 1",
    "session_id": "",
    "totalSeats": 329,
    "available": 10,
    "sold": 319,
    "gross": 319000,
    "occupancy": "96.96%",
    "source": "District",
    "date": "20260109",
    "chain": "Balaji 4k Atmos Cinemas"
  },
  {
    "movie": "Jana Nayagan [2D | Tamil]",
    "city": "Kollengode",
    "state": "Kerala",
    "venue": "Gowri Movie House A/C 2K Dolby 7.1, Ootra, Kollengode",
    "address": "Pudunagaram Kollengode Rd, Ootra, Kollengode, Kerala 678506, India",
    "time": "08:45 PM",
    "audi": "SCREEN 1",
    "session_id": "",
    "totalSeats": 201,
    "available": 124,
    "sold": 77,
    "gross": 9240,
    "occupancy": "38.31%",
    "source": "District",
    "date": "20260109",
    "chain": "Ticketnew"
  },
  {
    "movie": "Jana Nayagan [2D | Tamil]",
    "city": "Kollengode",
    "state": "Kerala",
    "venue": "Gowri Movie House A/C 2K Dolby 7.1, Ootra, Kollengode",
    "address": "Pudunagaram Kollengode Rd, Ootra, Kollengode, Kerala 678506, India",
    "time": "01:50 PM",
    "audi": "SCREEN 1",
    "session_id": "",
    "totalSeats": 201,
    "available": 190,
    "sold": 11,
    "gross": 1320,
    "occupancy": "5.47%",
    "source": "District",
    "date": "20260109",
    "chain": "Ticketnew"
  },
  {
    "movie": "Jana Nayagan [2D | Tamil]",
    "city": "Kollengode",
    "state": "Kerala",
    "venue": "Gowri Movie House A/C 2K Dolby 7.1, Ootra, Kollengode",
    "address": "Pudunagaram Kollengode Rd, Ootra, Kollengode, Kerala 678506, India",
    "time": "05:30 PM",
    "audi": "SCREEN 1",
    "session_id": "",
    "totalSeats": 201,
    "available": 172,
    "sold": 29,
    "gross": 3480,
    "occupancy": "14.43%",
    "source": "District",
    "date": "20260109",
    "chain": "Ticketnew"
  },
  {
    "movie": "Jana Nayagan [2D | Tamil]",
    "city": "Kollengode",
    "state": "Kerala",
    "venue": "Gowri Movie House A/C 2K Dolby 7.1, Ootra, Kollengode",
    "address": "Pudunagaram Kollengode Rd, Ootra, Kollengode, Kerala 678506, India",
    "time": "10:40 AM",
    "audi": "SCREEN 1",
    "session_id": "",
    "totalSeats": 201,
    "available": 155,
    "sold": 46,
    "gross": 5520,
    "occupancy": "22.89%",
    "source": "District",
    "date": "20260109",
    "chain": "Ticketnew"
  },
  {
    "movie": "Jana Nayagan [2D | Tamil]",
    "city": "Alappuzha",
    "state": "Kerala",
    "venue": "PAN CINEMAS 4K RGB LASER, Alappuzha",
    "address": "Vatikad Road, Kaichoondi, Alappuzha, Kerala 688013, India",
    "time": "09:40 AM",
    "audi": "SCREEN 3",
    "session_id": "",
    "totalSeats": 291,
    "available": 245,
    "sold": 46,
    "gross": 8560,
    "occupancy": "15.81%",
    "source": "District",
    "date": "20260109",
    "chain": "Pan Cinema"
  },
  {
    "movie": "Jana Nayagan [2D | Tamil]",
    "city": "Alappuzha",
    "state": "Kerala",
    "venue": "PAN CINEMAS 4K RGB LASER, Alappuzha",
    "address": "Vatikad Road, Kaichoondi, Alappuzha, Kerala 688013, India",
    "time": "08:40 PM",
    "audi": "SCREEN 3",
    "session_id": "",
    "totalSeats": 291,
    "available": 187,
    "sold": 104,
    "gross": 19350,
    "occupancy": "35.74%",
    "source": "District",
    "date": "20260109",
    "chain": "Pan Cinema"
  },
  {
    "movie": "Jana Nayagan [2D | Tamil]",
    "city": "Alappuzha",
    "state": "Kerala",
    "venue": "PAN CINEMAS 4K RGB LASER, Alappuzha",
    "address": "Vatikad Road, Kaichoondi, Alappuzha, Kerala 688013, India",
    "time": "01:20 PM",
    "audi": "SCREEN 3",
    "session_id": "",
    "totalSeats": 291,
    "available": 282,
    "sold": 9,
    "gross": 1760,
    "occupancy": "3.09%",
    "source": "District",
    "date": "20260109",
    "chain": "Pan Cinema"
  },
  {
    "movie": "Jana Nayagan [2D | Tamil]",
    "city": "Alappuzha",
    "state": "Kerala",
    "venue": "PAN CINEMAS 4K RGB LASER, Alappuzha",
    "address": "Vatikad Road, Kaichoondi, Alappuzha, Kerala 688013, India",
    "time": "05:00 PM",
    "audi": "SCREEN 3",
    "session_id": "",
    "totalSeats": 291,
    "available": 275,
    "sold": 16,
    "gross": 2880,
    "occupancy": "5.5%",
    "source": "District",
    "date": "20260109",
    "chain": "Pan Cinema"
  },
  {
    "movie": "Jana Nayagan [2D | Tamil]",
    "city": "Alappuzha",
    "state": "Kerala",
    "venue": "AEC Cinemas 4K ATMOS 360 Surround, Alappuzha ",
    "address": "AEC Cinemas, AVJ Junction, Erezha, Mullakkal, Alappuzha, Kerala 688011, India",
    "time": "09:30 AM",
    "audi": "AUDI 1",
    "session_id": "",
    "totalSeats": 321,
    "available": 244,
    "sold": 77,
    "gross": 14360,
    "occupancy": "23.99%",
    "source": "District",
    "date": "20260109",
    "chain": "Aec Cinema"
  },
  {
    "movie": "Jana Nayagan [2D | Tamil]",
    "city": "Alappuzha",
    "state": "Kerala",
    "venue": "AEC Cinemas 4K ATMOS 360 Surround, Alappuzha ",
    "address": "AEC Cinemas, AVJ Junction, Erezha, Mullakkal, Alappuzha, Kerala 688011, India",
    "time": "01:00 PM",
    "audi": "AUDI 1",
    "session_id": "",
    "totalSeats": 321,
    "available": 311,
    "sold": 10,
    "gross": 1800,
    "occupancy": "3.12%",
    "source": "District",
    "date": "20260109",
    "chain": "Aec Cinema"
  },
  {
    "movie": "Jana Nayagan [2D | Tamil]",
    "city": "Alappuzha",
    "state": "Kerala",
    "venue": "AEC Cinemas 4K ATMOS 360 Surround, Alappuzha ",
    "address": "AEC Cinemas, AVJ Junction, Erezha, Mullakkal, Alappuzha, Kerala 688011, India",
    "time": "08:00 PM",
    "audi": "AUDI 1",
    "session_id": "",
    "totalSeats": 321,
    "available": 219,
    "sold": 102,
    "gross": 19340,
    "occupancy": "31.78%",
    "source": "District",
    "date": "20260109",
    "chain": "Aec Cinema"
  },
  {
    "movie": "Jana Nayagan [2D | Tamil]",
    "city": "Alappuzha",
    "state": "Kerala",
    "venue": "AEC Cinemas 4K ATMOS 360 Surround, Alappuzha ",
    "address": "AEC Cinemas, AVJ Junction, Erezha, Mullakkal, Alappuzha, Kerala 688011, India",
    "time": "06:00 PM",
    "audi": "AUDI 2",
    "session_id": "",
    "totalSeats": 113,
    "available": 108,
    "sold": 5,
    "gross": 750,
    "occupancy": "4.42%",
    "source": "District",
    "date": "20260109",
    "chain": "Aec Cinema"
  },
  {
    "movie": "Jana Nayagan [2D | Tamil]",
    "city": "Alappuzha",
    "state": "Kerala",
    "venue": "AEC Cinemas 4K ATMOS 360 Surround, Alappuzha ",
    "address": "AEC Cinemas, AVJ Junction, Erezha, Mullakkal, Alappuzha, Kerala 688011, India",
    "time": "04:30 PM",
    "audi": "AUDI 1",
    "session_id": "",
    "totalSeats": 321,
    "available": 302,
    "sold": 19,
    "gross": 3390,
    "occupancy": "5.92%",
    "source": "District",
    "date": "20260109",
    "chain": "Aec Cinema"
  },
  {
    "movie": "Jana Nayagan [2D | Tamil]",
    "city": "Alappuzha",
    "state": "Kerala",
    "venue": "AEC Cinemas 4K ATMOS 360 Surround, Alappuzha ",
    "address": "AEC Cinemas, AVJ Junction, Erezha, Mullakkal, Alappuzha, Kerala 688011, India",
    "time": "11:00 AM",
    "audi": "AUDI 2",
    "session_id": "",
    "totalSeats": 113,
    "available": 108,
    "sold": 5,
    "gross": 850,
    "occupancy": "4.42%",
    "source": "District",
    "date": "20260109",
    "chain": "Aec Cinema"
  },
  {
    "movie": "Jana Nayagan [2D | Tamil]",
    "city": "Alappuzha",
    "state": "Kerala",
    "venue": "AEC Cinemas 4K ATMOS 360 Surround, Alappuzha ",
    "address": "AEC Cinemas, AVJ Junction, Erezha, Mullakkal, Alappuzha, Kerala 688011, India",
    "time": "09:30 PM",
    "audi": "AUDI 2",
    "session_id": "",
    "totalSeats": 113,
    "available": 89,
    "sold": 24,
    "gross": 3700,
    "occupancy": "21.24%",
    "source": "District",
    "date": "20260109",
    "chain": "Aec Cinema"
  },
  {
    "movie": "Jana Nayagan [2D | Tamil]",
    "city": "Alappuzha",
    "state": "Kerala",
    "venue": "AEC Cinemas 4K ATMOS 360 Surround, Alappuzha ",
    "address": "AEC Cinemas, AVJ Junction, Erezha, Mullakkal, Alappuzha, Kerala 688011, India",
    "time": "06:15 AM",
    "audi": "AUDI 2",
    "session_id": "",
    "totalSeats": 113,
    "available": 0,
    "sold": 113,
    "gross": 17700,
    "occupancy": "100.0%",
    "source": "District",
    "date": "20260109",
    "chain": "Aec Cinema"
  },
  {
    "movie": "Jana Nayagan [2D | Tamil]",
    "city": "Alappuzha",
    "state": "Kerala",
    "venue": "AEC Cinemas 4K ATMOS 360 Surround, Alappuzha ",
    "address": "AEC Cinemas, AVJ Junction, Erezha, Mullakkal, Alappuzha, Kerala 688011, India",
    "time": "02:30 PM",
    "audi": "AUDI 2",
    "session_id": "",
    "totalSeats": 113,
    "available": 109,
    "sold": 4,
    "gross": 650,
    "occupancy": "3.54%",
    "source": "District",
    "date": "20260109",
    "chain": "Aec Cinema"
  },
  {
    "movie": "Jana Nayagan [2D | Tamil]",
    "city": "Alappuzha",
    "state": "Kerala",
    "venue": "AEC Cinemas 4K ATMOS 360 Surround, Alappuzha ",
    "address": "AEC Cinemas, AVJ Junction, Erezha, Mullakkal, Alappuzha, Kerala 688011, India",
    "time": "11:30 PM",
    "audi": "AUDI 1",
    "session_id": "",
    "totalSeats": 321,
    "available": 291,
    "sold": 30,
    "gross": 5610,
    "occupancy": "9.35%",
    "source": "District",
    "date": "20260109",
    "chain": "Aec Cinema"
  },
  {
    "movie": "Jana Nayagan [2D | Tamil]",
    "city": "Alappuzha",
    "state": "Kerala",
    "venue": "AEC Cinemas 4K ATMOS 360 Surround, Alappuzha ",
    "address": "AEC Cinemas, AVJ Junction, Erezha, Mullakkal, Alappuzha, Kerala 688011, India",
    "time": "06:00 AM",
    "audi": "AUDI 1",
    "session_id": "",
    "totalSeats": 321,
    "available": 0,
    "sold": 321,
    "gross": 57100,
    "occupancy": "100.0%",
    "source": "District",
    "date": "20260109",
    "chain": "Aec Cinema"
  },
  {
    "movie": "Jana Nayagan [2D | Tamil]",
    "city": "Amballur",
    "state": "Kerala",
    "venue": "Chand V Sreerama Movies, Pudukkad, Amballur",
    "address": "Pudukkad, P.O, Thrissur, Amballur, Kerala 680301, India",
    "time": "11:30 AM",
    "audi": "SCREEN 2",
    "session_id": "",
    "totalSeats": 424,
    "available": 420,
    "sold": 4,
    "gross": 516,
    "occupancy": "0.94%",
    "source": "District",
    "date": "20260109",
    "chain": "Chandv"
  },
  {
    "movie": "Jana Nayagan [2D | Tamil]",
    "city": "Amballur",
    "state": "Kerala",
    "venue": "Chand V Sreerama Movies, Pudukkad, Amballur",
    "address": "Pudukkad, P.O, Thrissur, Amballur, Kerala 680301, India",
    "time": "06:00 AM",
    "audi": "SCREEN 2",
    "session_id": "",
    "totalSeats": 424,
    "available": 20,
    "sold": 404,
    "gross": 53850,
    "occupancy": "95.28%",
    "source": "District",
    "date": "20260109",
    "chain": "Chandv"
  },
  {
    "movie": "Jana Nayagan [2D | Tamil]",
    "city": "Amballur",
    "state": "Kerala",
    "venue": "Chand V Sreerama Movies, Pudukkad, Amballur",
    "address": "Pudukkad, P.O, Thrissur, Amballur, Kerala 680301, India",
    "time": "06:30 PM",
    "audi": "SCREEN 2",
    "session_id": "",
    "totalSeats": 424,
    "available": 406,
    "sold": 18,
    "gross": 2322,
    "occupancy": "4.25%",
    "source": "District",
    "date": "20260109",
    "chain": "Chandv"
  },
  {
    "movie": "Jana Nayagan [2D | Tamil]",
    "city": "Amballur",
    "state": "Kerala",
    "venue": "Chand V Sreerama Movies, Pudukkad, Amballur",
    "address": "Pudukkad, P.O, Thrissur, Amballur, Kerala 680301, India",
    "time": "03:00 PM",
    "audi": "SCREEN 2",
    "session_id": "",
    "totalSeats": 424,
    "available": 424,
    "sold": 0,
    "gross": 0,
    "occupancy": "0.0%",
    "source": "District",
    "date": "20260109",
    "chain": "Chandv"
  },
  {
    "movie": "Jana Nayagan [2D | Tamil]",
    "city": "Amballur",
    "state": "Kerala",
    "venue": "Chand V Sreerama Movies, Pudukkad, Amballur",
    "address": "Pudukkad, P.O, Thrissur, Amballur, Kerala 680301, India",
    "time": "10:00 PM",
    "audi": "SCREEN 2",
    "session_id": "",
    "totalSeats": 424,
    "available": 407,
    "sold": 17,
    "gross": 2193,
    "occupancy": "4.01%",
    "source": "District",
    "date": "20260109",
    "chain": "Chandv"
  },
  {
    "movie": "Jana Nayagan [2D | Tamil]",
    "city": "Arakkunnam",
    "state": "Kerala",
    "venue": "PAN CINEMAS 4K ATMOS, Arakkunnam",
    "address": "Near St. Joseph Catholic Church, Arakkunnam - Piravom Road, Ernakulam, Kerala 682313, India",
    "time": "09:40 AM",
    "audi": "SCREEN 2",
    "session_id": "",
    "totalSeats": 172,
    "available": 146,
    "sold": 26,
    "gross": 4820,
    "occupancy": "15.12%",
    "source": "District",
    "date": "20260109",
    "chain": "Pan Cinema"
  },
  {
    "movie": "Jana Nayagan [2D | Tamil]",
    "city": "Arakkunnam",
    "state": "Kerala",
    "venue": "PAN CINEMAS 4K ATMOS, Arakkunnam",
    "address": "Near St. Joseph Catholic Church, Arakkunnam - Piravom Road, Ernakulam, Kerala 682313, India",
    "time": "03:30 PM",
    "audi": "SCREEN 1",
    "session_id": "",
    "totalSeats": 172,
    "available": 162,
    "sold": 10,
    "gross": 1700,
    "occupancy": "5.81%",
    "source": "District",
    "date": "20260109",
    "chain": "Pan Cinema"
  },
  {
    "movie": "Jana Nayagan [2D | Tamil]",
    "city": "Arakkunnam",
    "state": "Kerala",
    "venue": "PAN CINEMAS 4K ATMOS, Arakkunnam",
    "address": "Near St. Joseph Catholic Church, Arakkunnam - Piravom Road, Ernakulam, Kerala 682313, India",
    "time": "06:15 AM",
    "audi": "SCREEN 1",
    "session_id": "",
    "totalSeats": 172,
    "available": 103,
    "sold": 69,
    "gross": 12290,
    "occupancy": "40.12%",
    "source": "District",
    "date": "20260109",
    "chain": "Pan Cinema"
  },
  {
    "movie": "Jana Nayagan [2D | Tamil]",
    "city": "Arakkunnam",
    "state": "Kerala",
    "venue": "PAN CINEMAS 4K ATMOS, Arakkunnam",
    "address": "Near St. Joseph Catholic Church, Arakkunnam - Piravom Road, Ernakulam, Kerala 682313, India",
    "time": "11:00 PM",
    "audi": "SCREEN 2",
    "session_id": "",
    "totalSeats": 172,
    "available": 134,
    "sold": 38,
    "gross": 6620,
    "occupancy": "22.09%",
    "source": "District",
    "date": "20260109",
    "chain": "Pan Cinema"
  },
  {
    "movie": "Jana Nayagan [2D | Tamil]",
    "city": "Chalakudy",
    "state": "Kerala",
    "venue": "Surabhi Movies 70 mm 4K RGB Laser 3D DOLBY, South Junction, Chalakudy",
    "address": "South Junction, Thrissur,Chalakudy,Kerala,68037",
    "time": "04:30 PM",
    "audi": "SCREEN 1 - 4K ",
    "session_id": "",
    "totalSeats": 625,
    "available": 529,
    "sold": 96,
    "gross": 14400,
    "occupancy": "15.36%",
    "source": "District",
    "date": "20260109",
    "chain": "Surabhi Movies"
  },
  {
    "movie": "Jana Nayagan [2D | Tamil]",
    "city": "Chalakudy",
    "state": "Kerala",
    "venue": "Surabhi Movies 70 mm 4K RGB Laser 3D DOLBY, South Junction, Chalakudy",
    "address": "South Junction, Thrissur,Chalakudy,Kerala,68037",
    "time": "09:30 AM",
    "audi": "SCREEN 1 - 4K ",
    "session_id": "",
    "totalSeats": 625,
    "available": 446,
    "sold": 179,
    "gross": 26850,
    "occupancy": "28.64%",
    "source": "District",
    "date": "20260109",
    "chain": "Surabhi Movies"
  },
  {
    "movie": "Jana Nayagan [2D | Tamil]",
    "city": "Chalakudy",
    "state": "Kerala",
    "venue": "Surabhi Movies 70 mm 4K RGB Laser 3D DOLBY, South Junction, Chalakudy",
    "address": "South Junction, Thrissur,Chalakudy,Kerala,68037",
    "time": "11:55 PM",
    "audi": "SCREEN 1 - 4K ",
    "session_id": "",
    "totalSeats": 625,
    "available": 521,
    "sold": 104,
    "gross": 15600,
    "occupancy": "16.64%",
    "source": "District",
    "date": "20260109",
    "chain": "Surabhi Movies"
  },
  {
    "movie": "Jana Nayagan [2D | Tamil]",
    "city": "Chalakudy",
    "state": "Kerala",
    "venue": "Surabhi Movies 70 mm 4K RGB Laser 3D DOLBY, South Junction, Chalakudy",
    "address": "South Junction, Thrissur,Chalakudy,Kerala,68037",
    "time": "08:30 PM",
    "audi": "SCREEN 1 - 4K ",
    "session_id": "",
    "totalSeats": 625,
    "available": 331,
    "sold": 294,
    "gross": 44100,
    "occupancy": "47.04%",
    "source": "District",
    "date": "20260109",
    "chain": "Surabhi Movies"
  },
  {
    "movie": "Jana Nayagan [2D | Tamil]",
    "city": "Chalakudy",
    "state": "Kerala",
    "venue": "Surabhi Movies 70 mm 4K RGB Laser 3D DOLBY, South Junction, Chalakudy",
    "address": "South Junction, Thrissur,Chalakudy,Kerala,68037",
    "time": "06:00 AM",
    "audi": "SCREEN 1 - 4K ",
    "session_id": "",
    "totalSeats": 625,
    "available": 31,
    "sold": 594,
    "gross": 89100,
    "occupancy": "95.04%",
    "source": "District",
    "date": "20260109",
    "chain": "Surabhi Movies"
  },
  {
    "movie": "Jana Nayagan [2D | Tamil]",
    "city": "Chalakudy",
    "state": "Kerala",
    "venue": "Surabhi Movies 70 mm 4K RGB Laser 3D DOLBY, South Junction, Chalakudy",
    "address": "South Junction, Thrissur,Chalakudy,Kerala,68037",
    "time": "01:00 PM",
    "audi": "SCREEN 1 - 4K ",
    "session_id": "",
    "totalSeats": 625,
    "available": 544,
    "sold": 81,
    "gross": 12150,
    "occupancy": "12.96%",
    "source": "District",
    "date": "20260109",
    "chain": "Surabhi Movies"
  },
  {
    "movie": "Jana Nayagan [2D | Tamil]",
    "city": "Chalakudy",
    "state": "Kerala",
    "venue": "Surabhi Movies 70 mm 4K RGB Laser 3D DOLBY, South Junction, Chalakudy",
    "address": "South Junction, Thrissur,Chalakudy,Kerala,68037",
    "time": "06:00 AM",
    "audi": "SCREEN 2 - 4K LASER",
    "session_id": "",
    "totalSeats": 315,
    "available": 151,
    "sold": 164,
    "gross": 24800,
    "occupancy": "52.06%",
    "source": "District",
    "date": "20260109",
    "chain": "Surabhi Movies"
  },
  {
    "movie": "Jana Nayagan [2D | Tamil]",
    "city": "Chalakudy",
    "state": "Kerala",
    "venue": "D Cinemas 4K, South Junction, Chalakudy",
    "address": "South Junction, Chalakudy, Kerala 680307, India",
    "time": "01:20 PM",
    "audi": "SCREEN 1 4K",
    "session_id": "",
    "totalSeats": 417,
    "available": 349,
    "sold": 68,
    "gross": 10800,
    "occupancy": "16.31%",
    "source": "District",
    "date": "20260109",
    "chain": "D Cinema"
  },
  {
    "movie": "Jana Nayagan [2D | Tamil]",
    "city": "Chalakudy",
    "state": "Kerala",
    "venue": "D Cinemas 4K, South Junction, Chalakudy",
    "address": "South Junction, Chalakudy, Kerala 680307, India",
    "time": "05:00 PM",
    "audi": "SCREEN 1 4K",
    "session_id": "",
    "totalSeats": 417,
    "available": 311,
    "sold": 106,
    "gross": 16500,
    "occupancy": "25.42%",
    "source": "District",
    "date": "20260109",
    "chain": "D Cinema"
  },
  {
    "movie": "Jana Nayagan [2D | Tamil]",
    "city": "Chalakudy",
    "state": "Kerala",
    "venue": "D Cinemas 4K, South Junction, Chalakudy",
    "address": "South Junction, Chalakudy, Kerala 680307, India",
    "time": "08:40 PM",
    "audi": "SCREEN 1 4K",
    "session_id": "",
    "totalSeats": 417,
    "available": 209,
    "sold": 208,
    "gross": 32700,
    "occupancy": "49.88%",
    "source": "District",
    "date": "20260109",
    "chain": "D Cinema"
  },
  {
    "movie": "Jana Nayagan [2D | Tamil]",
    "city": "Chalakudy",
    "state": "Kerala",
    "venue": "D Cinemas 4K, South Junction, Chalakudy",
    "address": "South Junction, Chalakudy, Kerala 680307, India",
    "time": "09:40 AM",
    "audi": "SCREEN 1 4K",
    "session_id": "",
    "totalSeats": 417,
    "available": 297,
    "sold": 120,
    "gross": 19050,
    "occupancy": "28.78%",
    "source": "District",
    "date": "20260109",
    "chain": "D Cinema"
  },
  {
    "movie": "Jana Nayagan [2D | Tamil]",
    "city": "Chalakudy",
    "state": "Kerala",
    "venue": "D Cinemas 4K, South Junction, Chalakudy",
    "address": "South Junction, Chalakudy, Kerala 680307, India",
    "time": "11:59 PM",
    "audi": "SCREEN 1 4K",
    "session_id": "",
    "totalSeats": 417,
    "available": 345,
    "sold": 72,
    "gross": 11400,
    "occupancy": "17.27%",
    "source": "District",
    "date": "20260109",
    "chain": "D Cinema"
  },
  {
    "movie": "Jana Nayagan [2D | Tamil]",
    "city": "Irinjalakuda",
    "state": "Kerala",
    "venue": "Chembakassery Cinemas 4K 3D Dolby Atmos, Temple Road, Irinjalakuda",
    "address": "Temple Rd, Irinjalakuda, Kerala 680121, India",
    "time": "11:59 PM",
    "audi": "SCREEN 1 ",
    "session_id": "",
    "totalSeats": 646,
    "available": 365,
    "sold": 281,
    "gross": 37375.6,
    "occupancy": "43.5%",
    "source": "District",
    "date": "20260109",
    "chain": "Chembakassery Cinemas"
  },
  {
    "movie": "Jana Nayagan [2D | Tamil]",
    "city": "Irinjalakuda",
    "state": "Kerala",
    "venue": "Chembakassery Cinemas 4K 3D Dolby Atmos, Temple Road, Irinjalakuda",
    "address": "Temple Rd, Irinjalakuda, Kerala 680121, India",
    "time": "05:00 PM",
    "audi": "SCREEN 1 ",
    "session_id": "",
    "totalSeats": 646,
    "available": 363,
    "sold": 283,
    "gross": 36955.6,
    "occupancy": "43.81%",
    "source": "District",
    "date": "20260109",
    "chain": "Chembakassery Cinemas"
  },
  {
    "movie": "Jana Nayagan [2D | Tamil]",
    "city": "Irinjalakuda",
    "state": "Kerala",
    "venue": "Chembakassery Cinemas 4K 3D Dolby Atmos, Temple Road, Irinjalakuda",
    "address": "Temple Rd, Irinjalakuda, Kerala 680121, India",
    "time": "10:00 AM",
    "audi": "SCREEN 1 ",
    "session_id": "",
    "totalSeats": 646,
    "available": 346,
    "sold": 300,
    "gross": 39485.4,
    "occupancy": "46.44%",
    "source": "District",
    "date": "20260109",
    "chain": "Chembakassery Cinemas"
  },
  {
    "movie": "Jana Nayagan [2D | Tamil]",
    "city": "Irinjalakuda",
    "state": "Kerala",
    "venue": "Chembakassery Cinemas 4K 3D Dolby Atmos, Temple Road, Irinjalakuda",
    "address": "Temple Rd, Irinjalakuda, Kerala 680121, India",
    "time": "01:30 PM",
    "audi": "SCREEN 1 ",
    "session_id": "",
    "totalSeats": 646,
    "available": 366,
    "sold": 280,
    "gross": 36505.6,
    "occupancy": "43.34%",
    "source": "District",
    "date": "20260109",
    "chain": "Chembakassery Cinemas"
  },
  {
    "movie": "Jana Nayagan [2D | Tamil]",
    "city": "Irinjalakuda",
    "state": "Kerala",
    "venue": "Chembakassery Cinemas 4K 3D Dolby Atmos, Temple Road, Irinjalakuda",
    "address": "Temple Rd, Irinjalakuda, Kerala 680121, India",
    "time": "08:30 PM",
    "audi": "SCREEN 1 ",
    "session_id": "",
    "totalSeats": 646,
    "available": 319,
    "sold": 327,
    "gross": 44195.6,
    "occupancy": "50.62%",
    "source": "District",
    "date": "20260109",
    "chain": "Chembakassery Cinemas"
  },
  {
    "movie": "Jana Nayagan [2D | Tamil]",
    "city": "Kollam",
    "state": "Kerala",
    "venue": "Magic Frames Archana Cinemas 4K Laser Atmos, Anchal",
    "address": "Anchal, Kollam, Kerala 691581, India",
    "time": "06:00 AM",
    "audi": "SCREEN 2",
    "session_id": "",
    "totalSeats": 227,
    "available": 69,
    "sold": 158,
    "gross": 24427.0,
    "occupancy": "69.6%",
    "source": "District",
    "date": "20260109",
    "chain": "Magic Frame Theatre"
  },
  {
    "movie": "Jana Nayagan [2D | Tamil]",
    "city": "Koothattukulam",
    "state": "Kerala",
    "venue": "V Cinema, MC Road, Koothattukulam",
    "address": "MC Road, Koothattukulam, Kerala 686662, India",
    "time": "06:00 PM",
    "audi": "SCREEN 3 4K Dolby Atmos",
    "session_id": "",
    "totalSeats": 303,
    "available": 277,
    "sold": 26,
    "gross": 4340,
    "occupancy": "8.58%",
    "source": "District",
    "date": "20260109",
    "chain": "V Cinema"
  },
  {
    "movie": "Jana Nayagan [2D | Tamil]",
    "city": "Koothattukulam",
    "state": "Kerala",
    "venue": "V Cinema, MC Road, Koothattukulam",
    "address": "MC Road, Koothattukulam, Kerala 686662, India",
    "time": "09:30 PM",
    "audi": "SCREEN 3 4K Dolby Atmos",
    "session_id": "",
    "totalSeats": 303,
    "available": 202,
    "sold": 101,
    "gross": 16160,
    "occupancy": "33.33%",
    "source": "District",
    "date": "20260109",
    "chain": "V Cinema"
  },
  {
    "movie": "Jana Nayagan [2D | Tamil]",
    "city": "Koothattukulam",
    "state": "Kerala",
    "venue": "V Cinema, MC Road, Koothattukulam",
    "address": "MC Road, Koothattukulam, Kerala 686662, India",
    "time": "10:00 AM",
    "audi": "SCREEN 3 4K Dolby Atmos",
    "session_id": "",
    "totalSeats": 303,
    "available": 262,
    "sold": 41,
    "gross": 6830,
    "occupancy": "13.53%",
    "source": "District",
    "date": "20260109",
    "chain": "V Cinema"
  },
  {
    "movie": "Jana Nayagan [2D | Tamil]",
    "city": "Koothattukulam",
    "state": "Kerala",
    "venue": "V Cinema, MC Road, Koothattukulam",
    "address": "MC Road, Koothattukulam, Kerala 686662, India",
    "time": "02:00 PM",
    "audi": "SCREEN 3 4K Dolby Atmos",
    "session_id": "",
    "totalSeats": 303,
    "available": 282,
    "sold": 21,
    "gross": 3360,
    "occupancy": "6.93%",
    "source": "District",
    "date": "20260109",
    "chain": "V Cinema"
  },
  {
    "movie": "Jana Nayagan [2D | Tamil]",
    "city": "Kottarakara",
    "state": "Kerala",
    "venue": "Minerva Empire Cinemaz, Chandamukku, Kottarakara",
    "address": "Chandamukku, Kottarakkara, Kerala 691506, India",
    "time": "03:30 PM",
    "audi": "Screen 1 - 4k 7.1",
    "session_id": "",
    "totalSeats": 457,
    "available": 444,
    "sold": 13,
    "gross": 1950,
    "occupancy": "2.84%",
    "source": "District",
    "date": "20260109",
    "chain": "Minerva Empire Cinemaz"
  },
  {
    "movie": "Jana Nayagan [2D | Tamil]",
    "city": "Kottarakara",
    "state": "Kerala",
    "venue": "Minerva Empire Cinemaz, Chandamukku, Kottarakara",
    "address": "Chandamukku, Kottarakkara, Kerala 691506, India",
    "time": "09:30 AM",
    "audi": "Screen 1 - 4k 7.1",
    "session_id": "",
    "totalSeats": 457,
    "available": 0,
    "sold": 457,
    "gross": 68550,
    "occupancy": "100.0%",
    "source": "District",
    "date": "20260109",
    "chain": "Minerva Empire Cinemaz"
  },
  {
    "movie": "Jana Nayagan [2D | Tamil]",
    "city": "Kottarakara",
    "state": "Kerala",
    "venue": "Minerva Empire Cinemaz, Chandamukku, Kottarakara",
    "address": "Chandamukku, Kottarakkara, Kerala 691506, India",
    "time": "09:45 PM",
    "audi": "Screen 1 - 4k 7.1",
    "session_id": "",
    "totalSeats": 457,
    "available": 375,
    "sold": 82,
    "gross": 12300,
    "occupancy": "17.94%",
    "source": "District",
    "date": "20260109",
    "chain": "Minerva Empire Cinemaz"
  },
  {
    "movie": "Jana Nayagan [2D | Tamil]",
    "city": "Kottarakara",
    "state": "Kerala",
    "venue": "Minerva Empire Cinemaz, Chandamukku, Kottarakara",
    "address": "Chandamukku, Kottarakkara, Kerala 691506, India",
    "time": "06:45 PM",
    "audi": "Screen 1 - 4k 7.1",
    "session_id": "",
    "totalSeats": 457,
    "available": 393,
    "sold": 64,
    "gross": 9600,
    "occupancy": "14.0%",
    "source": "District",
    "date": "20260109",
    "chain": "Minerva Empire Cinemaz"
  },
  {
    "movie": "Jana Nayagan [2D | Tamil]",
    "city": "Kottarakara",
    "state": "Kerala",
    "venue": "Minerva Empire Cinemaz, Chandamukku, Kottarakara",
    "address": "Chandamukku, Kottarakkara, Kerala 691506, India",
    "time": "12:30 PM",
    "audi": "Screen 1 - 4k 7.1",
    "session_id": "",
    "totalSeats": 457,
    "available": 413,
    "sold": 44,
    "gross": 6600,
    "occupancy": "9.63%",
    "source": "District",
    "date": "20260109",
    "chain": "Minerva Empire Cinemaz"
  },
  {
    "movie": "Jana Nayagan [2D | Tamil]",
    "city": "Kunnamkulam",
    "state": "Kerala",
    "venue": "Bavana Movies Laser Dolby Atmos, Near New Bus Stand, Kunnamkulam",
    "address": "Near New Bus Stand, Bhavana Theatre Road, Kunnamkulam, Thrissur, Kerala 680503, India",
    "time": "11:15 AM",
    "audi": "LITTILE BAVANA",
    "session_id": "",
    "totalSeats": 172,
    "available": 167,
    "sold": 5,
    "gross": 750,
    "occupancy": "2.91%",
    "source": "District",
    "date": "20260109",
    "chain": "Bavana"
  },
  {
    "movie": "Jana Nayagan [2D | Tamil]",
    "city": "Kunnamkulam",
    "state": "Kerala",
    "venue": "Bavana Movies Laser Dolby Atmos, Near New Bus Stand, Kunnamkulam",
    "address": "Near New Bus Stand, Bhavana Theatre Road, Kunnamkulam, Thrissur, Kerala 680503, India",
    "time": "02:45 PM",
    "audi": "LITTILE BAVANA",
    "session_id": "",
    "totalSeats": 172,
    "available": 170,
    "sold": 2,
    "gross": 300,
    "occupancy": "1.16%",
    "source": "District",
    "date": "20260109",
    "chain": "Bavana"
  },
  {
    "movie": "Jana Nayagan [2D | Tamil]",
    "city": "Kunnamkulam",
    "state": "Kerala",
    "venue": "Bavana Movies Laser Dolby Atmos, Near New Bus Stand, Kunnamkulam",
    "address": "Near New Bus Stand, Bhavana Theatre Road, Kunnamkulam, Thrissur, Kerala 680503, India",
    "time": "06:00 AM",
    "audi": "BAVANA",
    "session_id": "",
    "totalSeats": 519,
    "available": 0,
    "sold": 519,
    "gross": 68850,
    "occupancy": "100.0%",
    "source": "District",
    "date": "20260109",
    "chain": "Bavana"
  },
  {
    "movie": "Jana Nayagan [2D | Tamil]",
    "city": "Kunnamkulam",
    "state": "Kerala",
    "venue": "Bavana Movies Laser Dolby Atmos, Near New Bus Stand, Kunnamkulam",
    "address": "Near New Bus Stand, Bhavana Theatre Road, Kunnamkulam, Thrissur, Kerala 680503, India",
    "time": "11:30 AM",
    "audi": "BAVANA",
    "session_id": "",
    "totalSeats": 519,
    "available": 508,
    "sold": 11,
    "gross": 1650,
    "occupancy": "2.12%",
    "source": "District",
    "date": "20260109",
    "chain": "Bavana"
  },
  {
    "movie": "Jana Nayagan [2D | Tamil]",
    "city": "Kunnamkulam",
    "state": "Kerala",
    "venue": "Bavana Movies Laser Dolby Atmos, Near New Bus Stand, Kunnamkulam",
    "address": "Near New Bus Stand, Bhavana Theatre Road, Kunnamkulam, Thrissur, Kerala 680503, India",
    "time": "06:15 PM",
    "audi": "LITTILE BAVANA",
    "session_id": "",
    "totalSeats": 172,
    "available": 166,
    "sold": 6,
    "gross": 900,
    "occupancy": "3.49%",
    "source": "District",
    "date": "20260109",
    "chain": "Bavana"
  },
  {
    "movie": "Jana Nayagan [2D | Tamil]",
    "city": "Kunnamkulam",
    "state": "Kerala",
    "venue": "Bavana Movies Laser Dolby Atmos, Near New Bus Stand, Kunnamkulam",
    "address": "Near New Bus Stand, Bhavana Theatre Road, Kunnamkulam, Thrissur, Kerala 680503, India",
    "time": "10:00 PM",
    "audi": "BAVANA",
    "session_id": "",
    "totalSeats": 519,
    "available": 517,
    "sold": 2,
    "gross": 300,
    "occupancy": "0.39%",
    "source": "District",
    "date": "20260109",
    "chain": "Bavana"
  },
  {
    "movie": "Jana Nayagan [2D | Tamil]",
    "city": "Kunnamkulam",
    "state": "Kerala",
    "venue": "Bavana Movies Laser Dolby Atmos, Near New Bus Stand, Kunnamkulam",
    "address": "Near New Bus Stand, Bhavana Theatre Road, Kunnamkulam, Thrissur, Kerala 680503, India",
    "time": "06:00 AM",
    "audi": "LITTILE BAVANA",
    "session_id": "",
    "totalSeats": 172,
    "available": 0,
    "sold": 172,
    "gross": 26710,
    "occupancy": "100.0%",
    "source": "District",
    "date": "20260109",
    "chain": "Bavana"
  },
  {
    "movie": "Jana Nayagan [2D | Tamil]",
    "city": "Kunnamkulam",
    "state": "Kerala",
    "venue": "Bavana Movies Laser Dolby Atmos, Near New Bus Stand, Kunnamkulam",
    "address": "Near New Bus Stand, Bhavana Theatre Road, Kunnamkulam, Thrissur, Kerala 680503, India",
    "time": "03:00 PM",
    "audi": "BAVANA",
    "session_id": "",
    "totalSeats": 519,
    "available": 519,
    "sold": 0,
    "gross": 0,
    "occupancy": "0.0%",
    "source": "District",
    "date": "20260109",
    "chain": "Bavana"
  },
  {
    "movie": "Jana Nayagan [2D | Tamil]",
    "city": "Kunnamkulam",
    "state": "Kerala",
    "venue": "Bavana Movies Laser Dolby Atmos, Near New Bus Stand, Kunnamkulam",
    "address": "Near New Bus Stand, Bhavana Theatre Road, Kunnamkulam, Thrissur, Kerala 680503, India",
    "time": "06:30 PM",
    "audi": "BAVANA",
    "session_id": "",
    "totalSeats": 519,
    "available": 506,
    "sold": 13,
    "gross": 1800,
    "occupancy": "2.5%",
    "source": "District",
    "date": "20260109",
    "chain": "Bavana"
  },
  {
    "movie": "Jana Nayagan [2D | Tamil]",
    "city": "Kunnamkulam",
    "state": "Kerala",
    "venue": "Bavana Movies Laser Dolby Atmos, Near New Bus Stand, Kunnamkulam",
    "address": "Near New Bus Stand, Bhavana Theatre Road, Kunnamkulam, Thrissur, Kerala 680503, India",
    "time": "09:45 PM",
    "audi": "LITTILE BAVANA",
    "session_id": "",
    "totalSeats": 172,
    "available": 165,
    "sold": 7,
    "gross": 1260,
    "occupancy": "4.07%",
    "source": "District",
    "date": "20260109",
    "chain": "Bavana"
  },
  {
    "movie": "Jana Nayagan [2D | Tamil]",
    "city": "Mala",
    "state": "Kerala",
    "venue": "Ganga Movies, Mala 4K Dolby Atmos",
    "address": "Ganga Movies, Mala,Kerala 680732, India",
    "time": "02:00 PM",
    "audi": "GANGA",
    "session_id": "",
    "totalSeats": 295,
    "available": 295,
    "sold": 0,
    "gross": 0,
    "occupancy": "0.0%",
    "source": "District",
    "date": "20260109",
    "chain": "Ganga Movies"
  },
  {
    "movie": "Jana Nayagan [2D | Tamil]",
    "city": "Mala",
    "state": "Kerala",
    "venue": "Ganga Movies, Mala 4K Dolby Atmos",
    "address": "Ganga Movies, Mala,Kerala 680732, India",
    "time": "06:00 AM",
    "audi": "GANGA",
    "session_id": "",
    "totalSeats": 295,
    "available": 215,
    "sold": 80,
    "gross": 12560,
    "occupancy": "27.12%",
    "source": "District",
    "date": "20260109",
    "chain": "Ganga Movies"
  },
  {
    "movie": "Jana Nayagan [2D | Tamil]",
    "city": "Mala",
    "state": "Kerala",
    "venue": "Ganga Movies, Mala 4K Dolby Atmos",
    "address": "Ganga Movies, Mala,Kerala 680732, India",
    "time": "06:00 PM",
    "audi": "GANGA",
    "session_id": "",
    "totalSeats": 295,
    "available": 293,
    "sold": 2,
    "gross": 300,
    "occupancy": "0.68%",
    "source": "District",
    "date": "20260109",
    "chain": "Ganga Movies"
  },
  {
    "movie": "Jana Nayagan [2D | Tamil]",
    "city": "Mala",
    "state": "Kerala",
    "venue": "Ganga Movies, Mala 4K Dolby Atmos",
    "address": "Ganga Movies, Mala,Kerala 680732, India",
    "time": "10:00 AM",
    "audi": "GANGA",
    "session_id": "",
    "totalSeats": 295,
    "available": 285,
    "sold": 10,
    "gross": 1580,
    "occupancy": "3.39%",
    "source": "District",
    "date": "20260109",
    "chain": "Ganga Movies"
  },
  {
    "movie": "Jana Nayagan [2D | Tamil]",
    "city": "Mala",
    "state": "Kerala",
    "venue": "Ganga Movies, Mala 4K Dolby Atmos",
    "address": "Ganga Movies, Mala,Kerala 680732, India",
    "time": "10:00 PM",
    "audi": "GANGA",
    "session_id": "",
    "totalSeats": 295,
    "available": 282,
    "sold": 13,
    "gross": 1950,
    "occupancy": "4.41%",
    "source": "District",
    "date": "20260109",
    "chain": "Ganga Movies"
  },
  {
    "movie": "Sarvam Maya [2D | Malayalam]",
    "city": "Mannarkkad",
    "state": "Kerala",
    "venue": "Shivasakthi Cinemas Dolby Atmos, Near Nellipuzha Junction, Mannarkkad",
    "address": "Near Nellipuzha Junction, Mannarkkad, Palakkad, Kerala 678582,India",
    "time": "02:30 PM",
    "audi": "SCREEN 1",
    "session_id": "",
    "totalSeats": 256,
    "available": 256,
    "sold": 0,
    "gross": 0,
    "occupancy": "0.0%",
    "source": "District",
    "date": "20260109",
    "chain": "Shivasakthi Cinemas"
  },
  {
    "movie": "Sarvam Maya [2D | Malayalam]",
    "city": "Mannarkkad",
    "state": "Kerala",
    "venue": "Shivasakthi Cinemas Dolby Atmos, Near Nellipuzha Junction, Mannarkkad",
    "address": "Near Nellipuzha Junction, Mannarkkad, Palakkad, Kerala 678582,India",
    "time": "11:00 AM",
    "audi": "SCREEN 1",
    "session_id": "",
    "totalSeats": 256,
    "available": 256,
    "sold": 0,
    "gross": 0,
    "occupancy": "0.0%",
    "source": "District",
    "date": "20260109",
    "chain": "Shivasakthi Cinemas"
  },
  {
    "movie": "Sarvam Maya [2D | Malayalam]",
    "city": "Mannarkkad",
    "state": "Kerala",
    "venue": "Shivasakthi Cinemas Dolby Atmos, Near Nellipuzha Junction, Mannarkkad",
    "address": "Near Nellipuzha Junction, Mannarkkad, Palakkad, Kerala 678582,India",
    "time": "09:30 PM",
    "audi": "SCREEN 1",
    "session_id": "",
    "totalSeats": 256,
    "available": 256,
    "sold": 0,
    "gross": 0,
    "occupancy": "0.0%",
    "source": "District",
    "date": "20260109",
    "chain": "Shivasakthi Cinemas"
  },
  {
    "movie": "Sarvam Maya [2D | Malayalam]",
    "city": "Mannarkkad",
    "state": "Kerala",
    "venue": "Shivasakthi Cinemas Dolby Atmos, Near Nellipuzha Junction, Mannarkkad",
    "address": "Near Nellipuzha Junction, Mannarkkad, Palakkad, Kerala 678582,India",
    "time": "06:30 PM",
    "audi": "SCREEN 1",
    "session_id": "",
    "totalSeats": 256,
    "available": 256,
    "sold": 0,
    "gross": 0,
    "occupancy": "0.0%",
    "source": "District",
    "date": "20260109",
    "chain": "Shivasakthi Cinemas"
  },
  {
    "movie": "Jana Nayagan [2D | Tamil]",
    "city": "Ottapalam",
    "state": "Kerala",
    "venue": "Dreamax Cinemas 2K 7. 1 Surround, Mayannur, Ottapalam",
    "address": "Dreamax Cinemas, Chelakkara, Mayannur-Ottapalam Rd, Mayannur, Kerala, 679106, India",
    "time": "08:00 PM",
    "audi": "NILA",
    "session_id": "",
    "totalSeats": 200,
    "available": 191,
    "sold": 9,
    "gross": 1168.2,
    "occupancy": "4.5%",
    "source": "District",
    "date": "20260109",
    "chain": "Dreamax Cinemas 2k 7. 1 Surround Mayannur"
  },
  {
    "movie": "Jana Nayagan [2D | Tamil]",
    "city": "Ottapalam",
    "state": "Kerala",
    "venue": "Dreamax Cinemas 2K 7. 1 Surround, Mayannur, Ottapalam",
    "address": "Dreamax Cinemas, Chelakkara, Mayannur-Ottapalam Rd, Mayannur, Kerala, 679106, India",
    "time": "01:00 PM",
    "audi": "NILA",
    "session_id": "",
    "totalSeats": 200,
    "available": 198,
    "sold": 2,
    "gross": 259.6,
    "occupancy": "1.0%",
    "source": "District",
    "date": "20260109",
    "chain": "Dreamax Cinemas 2k 7. 1 Surround Mayannur"
  },
  {
    "movie": "Jana Nayagan [2D | Tamil]",
    "city": "Ottapalam",
    "state": "Kerala",
    "venue": "Dreamax Cinemas 2K 7. 1 Surround, Mayannur, Ottapalam",
    "address": "Dreamax Cinemas, Chelakkara, Mayannur-Ottapalam Rd, Mayannur, Kerala, 679106, India",
    "time": "06:00 AM",
    "audi": "NILA",
    "session_id": "",
    "totalSeats": 200,
    "available": 0,
    "sold": 200,
    "gross": 25960.0,
    "occupancy": "100.0%",
    "source": "District",
    "date": "20260109",
    "chain": "Dreamax Cinemas 2k 7. 1 Surround Mayannur"
  },
  {
    "movie": "Jana Nayagan [2D | Tamil]",
    "city": "Ottapalam",
    "state": "Kerala",
    "venue": "Dreamax Cinemas 2K 7. 1 Surround, Mayannur, Ottapalam",
    "address": "Dreamax Cinemas, Chelakkara, Mayannur-Ottapalam Rd, Mayannur, Kerala, 679106, India",
    "time": "04:30 PM",
    "audi": "NILA",
    "session_id": "",
    "totalSeats": 200,
    "available": 200,
    "sold": 0,
    "gross": 0.0,
    "occupancy": "0.0%",
    "source": "District",
    "date": "20260109",
    "chain": "Dreamax Cinemas 2k 7. 1 Surround Mayannur"
  },
  {
    "movie": "Jana Nayagan [2D | Tamil]",
    "city": "Ottapalam",
    "state": "Kerala",
    "venue": "Dreamax Cinemas 2K 7. 1 Surround, Mayannur, Ottapalam",
    "address": "Dreamax Cinemas, Chelakkara, Mayannur-Ottapalam Rd, Mayannur, Kerala, 679106, India",
    "time": "09:30 AM",
    "audi": "NILA",
    "session_id": "",
    "totalSeats": 200,
    "available": 95,
    "sold": 105,
    "gross": 13629.0,
    "occupancy": "52.5%",
    "source": "District",
    "date": "20260109",
    "chain": "Dreamax Cinemas 2k 7. 1 Surround Mayannur"
  },
  {
    "movie": "Jana Nayagan [2D | Tamil]",
    "city": "Ottapalam",
    "state": "Kerala",
    "venue": "Dreamax Cinemas 2K 7. 1 Surround, Mayannur, Ottapalam",
    "address": "Dreamax Cinemas, Chelakkara, Mayannur-Ottapalam Rd, Mayannur, Kerala, 679106, India",
    "time": "11:30 PM",
    "audi": "NILA",
    "session_id": "",
    "totalSeats": 200,
    "available": 200,
    "sold": 0,
    "gross": 0.0,
    "occupancy": "0.0%",
    "source": "District",
    "date": "20260109",
    "chain": "Dreamax Cinemas 2k 7. 1 Surround Mayannur"
  },
  {
    "movie": "Jana Nayagan [2D | Tamil]",
    "city": "Tirur",
    "state": "Kerala",
    "venue": "CNC Cinemaas RGB Laser 4K Atmos Triple Beam 3D, Tirur",
    "address": "BP Angadi Bypass, Kuttippuram Road, Malappuram(Dist), Tirur, Kerala 676102, India",
    "time": "06:20 AM",
    "audi": "AUDI 3",
    "session_id": "",
    "totalSeats": 200,
    "available": 199,
    "sold": 1,
    "gross": 160.0,
    "occupancy": "0.5%",
    "source": "District",
    "date": "20260109",
    "chain": "Cnc Cinemas"
  },
  {
    "movie": "Jana Nayagan [2D | Tamil]",
    "city": "Tirur",
    "state": "Kerala",
    "venue": "CNC Cinemaas RGB Laser 4K Atmos Triple Beam 3D, Tirur",
    "address": "BP Angadi Bypass, Kuttippuram Road, Malappuram(Dist), Tirur, Kerala 676102, India",
    "time": "06:00 AM",
    "audi": "AUDI 1",
    "session_id": "",
    "totalSeats": 369,
    "available": 84,
    "sold": 285,
    "gross": 53750,
    "occupancy": "77.24%",
    "source": "District",
    "date": "20260109",
    "chain": "Cnc Cinemas"
  },
  {
    "movie": "Jana Nayagan [2D | Tamil]",
    "city": "Tirur",
    "state": "Kerala",
    "venue": "CNC Cinemaas RGB Laser 4K Atmos Triple Beam 3D, Tirur",
    "address": "BP Angadi Bypass, Kuttippuram Road, Malappuram(Dist), Tirur, Kerala 676102, India",
    "time": "09:30 AM",
    "audi": "AUDI 1",
    "session_id": "",
    "totalSeats": 369,
    "available": 316,
    "sold": 53,
    "gross": 9650,
    "occupancy": "14.36%",
    "source": "District",
    "date": "20260109",
    "chain": "Cnc Cinemas"
  },
  {
    "movie": "Jana Nayagan [2D | Tamil]",
    "city": "Tirur",
    "state": "Kerala",
    "venue": "CNC Cinemaas RGB Laser 4K Atmos Triple Beam 3D, Tirur",
    "address": "BP Angadi Bypass, Kuttippuram Road, Malappuram(Dist), Tirur, Kerala 676102, India",
    "time": "04:30 PM",
    "audi": "AUDI 1",
    "session_id": "",
    "totalSeats": 369,
    "available": 280,
    "sold": 89,
    "gross": 16600,
    "occupancy": "24.12%",
    "source": "District",
    "date": "20260109",
    "chain": "Cnc Cinemas"
  },
  {
    "movie": "Jana Nayagan [2D | Tamil]",
    "city": "Tirur",
    "state": "Kerala",
    "venue": "CNC Cinemaas RGB Laser 4K Atmos Triple Beam 3D, Tirur",
    "address": "BP Angadi Bypass, Kuttippuram Road, Malappuram(Dist), Tirur, Kerala 676102, India",
    "time": "06:10 AM",
    "audi": "AUDI 2",
    "session_id": "",
    "totalSeats": 221,
    "available": 202,
    "sold": 19,
    "gross": 3350,
    "occupancy": "8.6%",
    "source": "District",
    "date": "20260109",
    "chain": "Cnc Cinemas"
  },
  {
    "movie": "Jana Nayagan [2D | Tamil]",
    "city": "Tirur",
    "state": "Kerala",
    "venue": "CNC Cinemaas RGB Laser 4K Atmos Triple Beam 3D, Tirur",
    "address": "BP Angadi Bypass, Kuttippuram Road, Malappuram(Dist), Tirur, Kerala 676102, India",
    "time": "11:20 PM",
    "audi": "AUDI 1",
    "session_id": "",
    "totalSeats": 369,
    "available": 313,
    "sold": 56,
    "gross": 11800,
    "occupancy": "15.18%",
    "source": "District",
    "date": "20260109",
    "chain": "Cnc Cinemas"
  },
  {
    "movie": "Jana Nayagan [2D | Tamil]",
    "city": "Tirur",
    "state": "Kerala",
    "venue": "CNC Cinemaas RGB Laser 4K Atmos Triple Beam 3D, Tirur",
    "address": "BP Angadi Bypass, Kuttippuram Road, Malappuram(Dist), Tirur, Kerala 676102, India",
    "time": "08:00 PM",
    "audi": "AUDI 1",
    "session_id": "",
    "totalSeats": 369,
    "available": 198,
    "sold": 171,
    "gross": 32200,
    "occupancy": "46.34%",
    "source": "District",
    "date": "20260109",
    "chain": "Cnc Cinemas"
  },
  {
    "movie": "Jana Nayagan [2D | Tamil]",
    "city": "Tirur",
    "state": "Kerala",
    "venue": "CNC Cinemaas RGB Laser 4K Atmos Triple Beam 3D, Tirur",
    "address": "BP Angadi Bypass, Kuttippuram Road, Malappuram(Dist), Tirur, Kerala 676102, India",
    "time": "01:00 PM",
    "audi": "AUDI 1",
    "session_id": "",
    "totalSeats": 369,
    "available": 332,
    "sold": 37,
    "gross": 6800,
    "occupancy": "10.03%",
    "source": "District",
    "date": "20260109",
    "chain": "Cnc Cinemas"
  },
  {
    "movie": "Jana Nayagan [2D | Tamil]",
    "city": "Kottakkal",
    "state": "Kerala",
    "venue": "Sangeeth 4K Laser & Lumiere Dolby Atmos, Vyapara Bhavan Road, Kottakkal",
    "address": "Vyapara Bhavan Rd, Kottakkal, Kerala 676503, India",
    "time": "10:00 AM",
    "audi": "Sangeeth",
    "session_id": "",
    "totalSeats": 443,
    "available": 338,
    "sold": 105,
    "gross": 11025,
    "occupancy": "23.7%",
    "source": "District",
    "date": "20260109",
    "chain": "Ticketnew"
  },
  {
    "movie": "Jana Nayagan [2D | Tamil]",
    "city": "Kottakkal",
    "state": "Kerala",
    "venue": "Sangeeth 4K Laser & Lumiere Dolby Atmos, Vyapara Bhavan Road, Kottakkal",
    "address": "Vyapara Bhavan Rd, Kottakkal, Kerala 676503, India",
    "time": "06:00 PM",
    "audi": "Sangeeth",
    "session_id": "",
    "totalSeats": 443,
    "available": 232,
    "sold": 211,
    "gross": 22155,
    "occupancy": "47.63%",
    "source": "District",
    "date": "20260109",
    "chain": "Ticketnew"
  },
  {
    "movie": "Jana Nayagan [2D | Tamil]",
    "city": "Kottakkal",
    "state": "Kerala",
    "venue": "Sangeeth 4K Laser & Lumiere Dolby Atmos, Vyapara Bhavan Road, Kottakkal",
    "address": "Vyapara Bhavan Rd, Kottakkal, Kerala 676503, India",
    "time": "06:00 AM",
    "audi": "Sangeeth",
    "session_id": "",
    "totalSeats": 443,
    "available": 0,
    "sold": 443,
    "gross": 46515,
    "occupancy": "100.0%",
    "source": "District",
    "date": "20260109",
    "chain": "Ticketnew"
  },
  {
    "movie": "Jana Nayagan [2D | Tamil]",
    "city": "Kottakkal",
    "state": "Kerala",
    "venue": "Sangeeth 4K Laser & Lumiere Dolby Atmos, Vyapara Bhavan Road, Kottakkal",
    "address": "Vyapara Bhavan Rd, Kottakkal, Kerala 676503, India",
    "time": "10:00 PM",
    "audi": "Sangeeth",
    "session_id": "",
    "totalSeats": 443,
    "available": 252,
    "sold": 191,
    "gross": 20055,
    "occupancy": "43.12%",
    "source": "District",
    "date": "20260109",
    "chain": "Ticketnew"
  },
  {
    "movie": "Jana Nayagan [2D | Tamil]",
    "city": "Kottakkal",
    "state": "Kerala",
    "venue": "Sangeeth 4K Laser & Lumiere Dolby Atmos, Vyapara Bhavan Road, Kottakkal",
    "address": "Vyapara Bhavan Rd, Kottakkal, Kerala 676503, India",
    "time": "02:00 PM",
    "audi": "Sangeeth",
    "session_id": "",
    "totalSeats": 443,
    "available": 386,
    "sold": 57,
    "gross": 5985,
    "occupancy": "12.87%",
    "source": "District",
    "date": "20260109",
    "chain": "Ticketnew"
  }
]