{
  "Mana Shankara Vara Prasad Garu [2D | Telugu]": {
    "shows": 30,
    "gross": 2325.0,
    "sold": 11,
    "totalSeats": 8597,
    "venues": 8,
    "cities": 8,
    "fastfilling": 0,
    "housefull": 0,
    "occupancy": 0.13,
    "details": [
      {
        "city": "Mulugu",
        "state": "Telangana",
        "venues": 1,
        "shows": 4,
        "gross": 0.0,
        "sold": 0,
        "totalSeats": 440,
        "fastfilling": 0,
        "housefull": 0,
        "occupancy": 0.0
      },
      {
        "city": "Nagari",
        "state": "Andhra Pradesh",
        "venues": 1,
        "shows": 2,
        "gross": 1200.0,
        "sold": 6,
        "totalSeats": 900,
        "fastfilling": 0,
        "housefull": 0,
        "occupancy": 0.67
      },
      {
        "city": "Jami",
        "state": "Andhra Pradesh",
        "venues": 1,
        "shows": 4,
        "gross": 0.0,
        "sold": 0,
        "totalSeats": 480,
        "fastfilling": 0,
        "housefull": 0,
        "occupancy": 0.0
      },
      {
        "city": "Kasibugga",
        "state": "Andhra Pradesh",
        "venues": 1,
        "shows": 4,
        "gross": 0.0,
        "sold": 0,
        "totalSeats": 741,
        "fastfilling": 0,
        "housefull": 0,
        "occupancy": 0.0
      },
      {
        "city": "Cherukupalli",
        "state": "Andhra Pradesh",
        "venues": 1,
        "shows": 4,
        "gross": 0.0,
        "sold": 0,
        "totalSeats": 1332,
        "fastfilling": 0,
        "housefull": 0,
        "occupancy": 0.0
      },
      {
        "city": "Suryapet",
        "state": "Telangana",
        "venues": 1,
        "shows": 4,
        "gross": 1125.0,
        "sold": 5,
        "totalSeats": 1796,
        "fastfilling": 0,
        "housefull": 0,
        "occupancy": 0.28
      },
      {
        "city": "Giddalur",
        "state": "Andhra Pradesh",
        "venues": 1,
        "shows": 4,
        "gross": 0.0,
        "sold": 0,
        "totalSeats": 1668,
        "fastfilling": 0,
        "housefull": 0,
        "occupancy": 0.0
      },
      {
        "city": "Bhuvanagiri",
        "state": "Telangana",
        "venues": 1,
        "shows": 4,
        "gross": 0.0,
        "sold": 0,
        "totalSeats": 1240,
        "fastfilling": 0,
        "housefull": 0,
        "occupancy": 0.0
      }
    ],
    "Chain_details": [
      {
        "chain": "Tirumala Kalamandir: Mulugu",
        "venues": 1,
        "shows": 4,
        "gross": 0.0,
        "sold": 0,
        "totalSeats": 440,
        "fastfilling": 0,
        "housefull": 0,
        "occupancy": 0.0
      },
      {
        "chain": "NMC Cinemas",
        "venues": 1,
        "shows": 2,
        "gross": 1200.0,
        "sold": 6,
        "totalSeats": 900,
        "fastfilling": 0,
        "housefull": 0,
        "occupancy": 0.67
      },
      {
        "chain": "Sri Lakshmi Narasimha (Jyothi Theater): Jami",
        "venues": 1,
        "shows": 4,
        "gross": 0.0,
        "sold": 0,
        "totalSeats": 480,
        "fastfilling": 0,
        "housefull": 0,
        "occupancy": 0.0
      },
      {
        "chain": "Justickets",
        "venues": 1,
        "shows": 4,
        "gross": 0.0,
        "sold": 0,
        "totalSeats": 741,
        "fastfilling": 0,
        "housefull": 0,
        "occupancy": 0.0
      },
      {
        "chain": "Sri Balaji Picture Palace: Cherukupalli",
        "venues": 1,
        "shows": 4,
        "gross": 0.0,
        "sold": 0,
        "totalSeats": 1332,
        "fastfilling": 0,
        "housefull": 0,
        "occupancy": 0.0
      },
      {
        "chain": "Primeshow Films",
        "venues": 2,
        "shows": 8,
        "gross": 1125.0,
        "sold": 5,
        "totalSeats": 3036,
        "fastfilling": 0,
        "housefull": 0,
        "occupancy": 0.16
      },
      {
        "chain": "Krishna Theater: Giddalur",
        "venues": 1,
        "shows": 4,
        "gross": 0.0,
        "sold": 0,
        "totalSeats": 1668,
        "fastfilling": 0,
        "housefull": 0,
        "occupancy": 0.0
      }
    ]
  },
  "Bhartha Mahasayulaku Wignyapthi [2D | Telugu]": {
    "shows": 4,
    "gross": 0.0,
    "sold": 0,
    "totalSeats": 1472,
    "venues": 1,
    "cities": 1,
    "fastfilling": 0,
    "housefull": 0,
    "occupancy": 0.0,
    "details": [
      {
        "city": "Markapur",
        "state": "Andhra Pradesh",
        "venues": 1,
        "shows": 4,
        "gross": 0.0,
        "sold": 0,
        "totalSeats": 1472,
        "fastfilling": 0,
        "housefull": 0,
        "occupancy": 0.0
      }
    ],
    "Chain_details": [
      {
        "chain": "Vijaya Theater: Markapur",
        "venues": 1,
        "shows": 4,
        "gross": 0.0,
        "sold": 0,
        "totalSeats": 1472,
        "fastfilling": 0,
        "housefull": 0,
        "occupancy": 0.0
      }
    ]
  },
  "The Raja Saab [2D | Telugu]": {
    "shows": 34,
    "gross": 57990.0,
    "sold": 194,
    "totalSeats": 7385,
    "venues": 8,
    "cities": 7,
    "fastfilling": 0,
    "housefull": 0,
    "occupancy": 2.63,
    "details": [
      {
        "city": "Nagari",
        "state": "Andhra Pradesh",
        "venues": 1,
        "shows": 2,
        "gross": 0.0,
        "sold": 0,
        "totalSeats": 900,
        "fastfilling": 0,
        "housefull": 0,
        "occupancy": 0.0
      },
      {
        "city": "Jangareddy Gudem",
        "state": "Andhra Pradesh",
        "venues": 2,
        "shows": 10,
        "gross": 57990.0,
        "sold": 194,
        "totalSeats": 2345,
        "fastfilling": 0,
        "housefull": 0,
        "occupancy": 8.27
      },
      {
        "city": "Huzurabad",
        "state": "Telangana",
        "venues": 1,
        "shows": 4,
        "gross": 0.0,
        "sold": 0,
        "totalSeats": 832,
        "fastfilling": 0,
        "housefull": 0,
        "occupancy": 0.0
      },
      {
        "city": "Ganapavaram",
        "state": "Andhra Pradesh",
        "venues": 1,
        "shows": 5,
        "gross": 0.0,
        "sold": 0,
        "totalSeats": 310,
        "fastfilling": 0,
        "housefull": 0,
        "occupancy": 0.0
      },
      {
        "city": "Jammikunta",
        "state": "Telangana",
        "venues": 1,
        "shows": 4,
        "gross": 0.0,
        "sold": 0,
        "totalSeats": 792,
        "fastfilling": 0,
        "housefull": 0,
        "occupancy": 0.0
      },
      {
        "city": "Chintalapudi",
        "state": "Andhra Pradesh",
        "venues": 1,
        "shows": 5,
        "gross": 0.0,
        "sold": 0,
        "totalSeats": 710,
        "fastfilling": 0,
        "housefull": 0,
        "occupancy": 0.0
      },
      {
        "city": "Giddalur",
        "state": "Andhra Pradesh",
        "venues": 1,
        "shows": 4,
        "gross": 0.0,
        "sold": 0,
        "totalSeats": 1496,
        "fastfilling": 0,
        "housefull": 0,
        "occupancy": 0.0
      }
    ],
    "Chain_details": [
      {
        "chain": "NMC Cinemas",
        "venues": 1,
        "shows": 2,
        "gross": 0.0,
        "sold": 0,
        "totalSeats": 900,
        "fastfilling": 0,
        "housefull": 0,
        "occupancy": 0.0
      },
      {
        "chain": "Sri Raja Rajeswari Talkies: Jangareddy Gudem",
        "venues": 1,
        "shows": 5,
        "gross": 0.0,
        "sold": 0,
        "totalSeats": 1350,
        "fastfilling": 0,
        "housefull": 0,
        "occupancy": 0.0
      },
      {
        "chain": "Y Screens Entertainment India Limited",
        "venues": 1,
        "shows": 5,
        "gross": 57990.0,
        "sold": 194,
        "totalSeats": 995,
        "fastfilling": 0,
        "housefull": 0,
        "occupancy": 19.5
      },
      {
        "chain": "Primeshow Films",
        "venues": 2,
        "shows": 8,
        "gross": 0.0,
        "sold": 0,
        "totalSeats": 1624,
        "fastfilling": 0,
        "housefull": 0,
        "occupancy": 0.0
      },
      {
        "chain": "Kumari Picture Palace A/C Dts: Ganapavaram",
        "venues": 1,
        "shows": 5,
        "gross": 0.0,
        "sold": 0,
        "totalSeats": 310,
        "fastfilling": 0,
        "housefull": 0,
        "occupancy": 0.0
      },
      {
        "chain": "Sarada Mini A/C Theatre: Chintalapudi",
        "venues": 1,
        "shows": 5,
        "gross": 0.0,
        "sold": 0,
        "totalSeats": 710,
        "fastfilling": 0,
        "housefull": 0,
        "occupancy": 0.0
      },
      {
        "chain": "Srinivasa Theater Giddalur",
        "venues": 1,
        "shows": 4,
        "gross": 0.0,
        "sold": 0,
        "totalSeats": 1496,
        "fastfilling": 0,
        "housefull": 0,
        "occupancy": 0.0
      }
    ]
  },
  "Chaphu [2D | Manipuri]": {
    "shows": 2,
    "gross": 2400.0,
    "sold": 8,
    "totalSeats": 678,
    "venues": 1,
    "cities": 1,
    "fastfilling": 0,
    "housefull": 0,
    "occupancy": 1.18,
    "details": [
      {
        "city": "Imphal",
        "state": "Manipur",
        "venues": 1,
        "shows": 2,
        "gross": 2400.0,
        "sold": 8,
        "totalSeats": 678,
        "fastfilling": 0,
        "housefull": 0,
        "occupancy": 1.18
      }
    ],
    "Chain_details": [
      {
        "chain": "TANTHA ENTERTAINMENT PRIVATE LIMITED",
        "venues": 1,
        "shows": 2,
        "gross": 2400.0,
        "sold": 8,
        "totalSeats": 678,
        "fastfilling": 0,
        "housefull": 0,
        "occupancy": 1.18
      }
    ]
  },
  "Parasakthi [2D | Tamil]": {
    "shows": 16,
    "gross": 83440.0,
    "sold": 492,
    "totalSeats": 10028,
    "venues": 4,
    "cities": 1,
    "fastfilling": 0,
    "housefull": 0,
    "occupancy": 4.91,
    "details": [
      {
        "city": "Trichy",
        "state": "Tamil Nadu",
        "venues": 4,
        "shows": 16,
        "gross": 83440.0,
        "sold": 492,
        "totalSeats": 10028,
        "fastfilling": 0,
        "housefull": 0,
        "occupancy": 4.91
      }
    ],
    "Chain_details": [
      {
        "chain": "Cauvery Theatre: Trichy",
        "venues": 1,
        "shows": 4,
        "gross": 6590.0,
        "sold": 39,
        "totalSeats": 2224,
        "fastfilling": 0,
        "housefull": 0,
        "occupancy": 1.75
      },
      {
        "chain": "Ramba Theatre Dolby Atmos: Trichy",
        "venues": 1,
        "shows": 4,
        "gross": 340.0,
        "sold": 2,
        "totalSeats": 2952,
        "fastfilling": 0,
        "housefull": 0,
        "occupancy": 0.07
      },
      {
        "chain": "Mega Star Theatre (2K): Trichy",
        "venues": 1,
        "shows": 4,
        "gross": 67770.0,
        "sold": 405,
        "totalSeats": 3072,
        "fastfilling": 0,
        "housefull": 0,
        "occupancy": 13.18
      },
      {
        "chain": "BHELEC Cinema: Trichy",
        "venues": 1,
        "shows": 4,
        "gross": 8740.0,
        "sold": 46,
        "totalSeats": 1780,
        "fastfilling": 0,
        "housefull": 0,
        "occupancy": 2.58
      }
    ]
  }
}